evan_utils/__init__.py
evan_utils/basic_functions.py
evan_utils/image_functions.py
evan_utils-0.0.5.dist-info/METADATA
evan_utils-0.0.5.dist-info/WHEEL
evan_utils-0.0.5.dist-info/licenses/LICENSE
evan_utils-0.0.5.dist-info/RECORD
